target_couchbase/__init__.py
target_couchbase/schema.py
target_couchbase-0.1.2.dist-info/AUTHORS.md
target_couchbase-0.1.2.dist-info/LICENSE
target_couchbase-0.1.2.dist-info/METADATA
target_couchbase-0.1.2.dist-info/WHEEL
target_couchbase-0.1.2.dist-info/entry_points.txt
target_couchbase-0.1.2.dist-info/top_level.txt
target_couchbase-0.1.2.dist-info/RECORD
