Metadata-Version: 2.1
Name: target-couchbase
Version: 0.1.2
Summary: Load data on Couchbase via singer.io
Home-page: https://github.com/anelendata/target_couchbase
Author: Daigo Tanaka, Anelen Co., LLC
License: UNKNOWN
Platform: UNKNOWN
Classifier: Development Status :: 4 - Beta
Classifier: License :: OSI Approved :: Apache Software License
Classifier: Operating System :: MacOS :: MacOS X
Classifier: Operating System :: POSIX :: Linux
Classifier: Programming Language :: Python :: 3.6
Classifier: Programming Language :: Python :: 3.7
Classifier: Programming Language :: Python :: 3.8
Requires-Dist: couchbase (>=3.0.8)
Requires-Dist: setuptools (>=40.3.0)
Requires-Dist: simplejson (==3.11.1)
Requires-Dist: singer-python (>=5.2.0)
